{"balances":[{"time_stamp":1425939063708,"balance-not-on-order":[{"amount":0.00688862,"currency":"BTC"},{"amount":0.0,"currency":"NBT"}]},{"time_stamp":1425939193590,"balance-not-on-order":[{"amount":0.00688862,"currency":"BTC"},{"amount":0.0,"currency":"NBT"}]},{"time_stamp":1425939323845,"balance-not-on-order":[{"amount":0.00688862,"currency":"BTC"},{"amount":0.0,"currency":"NBT"}]},{"time_stamp":1425939453978,"balance-not-on-order":[{"amount":0.00688862,"currency":"BTC"},{"amount":0.0,"currency":"NBT"}]},{"time_stamp":1425939583683,"balance-not-on-order":[{"amount":0.00688862,"currency":"BTC"},{"amount":0.0,"currency":"NBT"}]},{"time_stamp":1425939713634,"balance-not-on-order":[{"amount":0.00688862,"currency":"BTC"},{"amount":0.0,"currency":"NBT"}]},{"time_stamp":1425939973820,"balance-not-on-order":[{"amount":0.00688862,"currency":"BTC"},{"amount":0.0,"currency":"NBT"}]},{"time_stamp":1425940103629,"balance-not-on-order":[{"amount":0.00688862,"currency":"BTC"},{"amount":0.0,"currency":"NBT"}]},{"time_stamp":1425940233864,"balance-not-on-order":[{"amount":0.00688862,"currency":"BTC"},{"amount":0.0,"currency":"NBT"}]},{"time_stamp":1425940363773,"balance-not-on-order":[{"amount":0.00688862,"currency":"BTC"},{"amount":0.0,"currency":"NBT"}]},{"time_stamp":1425940493617,"balance-not-on-order":[{"amount":0.00688862,"currency":"BTC"},{"amount":0.0,"currency":"NBT"}]},{"time_stamp":1425940623738,"balance-not-on-order":[{"amount":0.00688862,"currency":"BTC"},{"amount":0.0,"currency":"NBT"}]},{"time_stamp":1425940883729,"balance-not-on-order":[{"amount":0.00688862,"currency":"BTC"},{"amount":0.0,"currency":"NBT"}]},{"time_stamp":1425941013668,"balance-not-on-order":[{"amount":0.00688862,"currency":"BTC"},{"amount":0.0,"currency":"NBT"}]},{"time_stamp":1425941144003,"balance-not-on-order":[{"amount":0.00688862,"currency":"BTC"},{"amount":0.0,"currency":"NBT"}]},{"time_stamp":1425941273668,"balance-not-on-order":[{"amount":0.00688862,"currency":"BTC"},{"amount":0.0,"currency":"NBT"}]},{"time_stamp":1425941403654,"balance-not-on-order":[{"amount":0.00688862,"currency":"BTC"},{"amount":0.0,"currency":"NBT"}]},{"time_stamp":1425941533616,"balance-not-on-order":[{"amount":0.00688862,"currency":"BTC"},{"amount":0.0,"currency":"NBT"}]},{"time_stamp":1425941793677,"balance-not-on-order":[{"amount":0.00311527,"currency":"BTC"},{"amount":1.5,"currency":"NBT"}]},{"time_stamp":1425941923641,"balance-not-on-order":[{"amount":0.00310677,"currency":"BTC"},{"amount":1.5,"currency":"NBT"}]},{"time_stamp":1425942053874,"balance-not-on-order":[{"amount":0.0031517,"currency":"BTC"},{"amount":1.5,"currency":"NBT"}]},{"time_stamp":1425942313746,"balance-not-on-order":[{"amount":0.00314708,"currency":"BTC"},{"amount":1.5,"currency":"NBT"}]},{"time_stamp":1425942443685,"balance-not-on-order":[{"amount":0.00315237,"currency":"BTC"},{"amount":1.5,"currency":"NBT"}]},{"time_stamp":1425942573681,"balance-not-on-order":[{"amount":0.00315237,"currency":"BTC"},{"amount":1.5,"currency":"NBT"}]},{"time_stamp":1425942703598,"balance-not-on-order":[{"amount":0.00315237,"currency":"BTC"},{"amount":1.5,"currency":"NBT"}]},{"time_stamp":1425942833595,"balance-not-on-order":[{"amount":0.00313884,"currency":"BTC"},{"amount":1.5,"currency":"NBT"}]},{"time_stamp":1425942964152,"balance-not-on-order":[{"amount":0.00314159,"currency":"BTC"},{"amount":1.5,"currency":"NBT"}]},{"time_stamp":1425943223592,"balance-not-on-order":[{"amount":0.00314619,"currency":"BTC"},{"amount":1.5,"currency":"NBT"}]},{"time_stamp":1425943353601,"balance-not-on-order":[{"amount":0.0031451,"currency":"BTC"},{"amount":1.5,"currency":"NBT"}]},{"time_stamp":1425943483602,"balance-not-on-order":[{"amount":0.0031452,"currency":"BTC"},{"amount":1.5,"currency":"NBT"}]},{"time_stamp":1425943613606,"balance-not-on-order":[{"amount":0.0031452,"currency":"BTC"},{"amount":1.5,"currency":"NBT"}]},{"time_stamp":1425943743682,"balance-not-on-order":[{"amount":0.00314136,"currency":"BTC"},{"amount":1.5,"currency":"NBT"}]},{"time_stamp":1425943873616,"balance-not-on-order":[{"amount":0.00314279,"currency":"BTC"},{"amount":1.5,"currency":"NBT"}]},{"time_stamp":1425944004243,"balance-not-on-order":[{"amount":0.00314279,"currency":"BTC"},{"amount":1.5,"currency":"NBT"}]},{"time_stamp":1425944133691,"balance-not-on-order":[{"amount":0.00314279,"currency":"BTC"},{"amount":1.5,"currency":"NBT"}]},{"time_stamp":1425944263750,"balance-not-on-order":[{"amount":0.003136,"currency":"BTC"},{"amount":1.5,"currency":"NBT"}]},{"time_stamp":1425944393637,"balance-not-on-order":[{"amount":0.00313447,"currency":"BTC"},{"amount":1.5,"currency":"NBT"}]},{"time_stamp":1425944653578,"balance-not-on-order":[{"amount":0.00313447,"currency":"BTC"},{"amount":1.5,"currency":"NBT"}]},{"time_stamp":1425944783948,"balance-not-on-order":[{"amount":0.00313589,"currency":"BTC"},{"amount":1.5,"currency":"NBT"}]},{"time_stamp":1425944913582,"balance-not-on-order":[{"amount":0.00313644,"currency":"BTC"},{"amount":1.5,"currency":"NBT"}]},{"time_stamp":1425945043739,"balance-not-on-order":[{"amount":0.00313644,"currency":"BTC"},{"amount":1.5,"currency":"NBT"}]},{"time_stamp":1425945173676,"balance-not-on-order":[{"amount":0.00313644,"currency":"BTC"},{"amount":1.5,"currency":"NBT"}]},{"time_stamp":1425945303687,"balance-not-on-order":[{"amount":0.00313327,"currency":"BTC"},{"amount":1.5,"currency":"NBT"}]},{"time_stamp":1425945563804,"balance-not-on-order":[{"amount":0.00313327,"currency":"BTC"},{"amount":1.5,"currency":"NBT"}]},{"time_stamp":1425945693681,"balance-not-on-order":[{"amount":0.00313578,"currency":"BTC"},{"amount":1.5,"currency":"NBT"}]},{"time_stamp":1425945823665,"balance-not-on-order":[{"amount":0.00313425,"currency":"BTC"},{"amount":1.5,"currency":"NBT"}]},{"time_stamp":1425945953628,"balance-not-on-order":[{"amount":0.00313425,"currency":"BTC"},{"amount":1.5,"currency":"NBT"}]},{"time_stamp":1425946083666,"balance-not-on-order":[{"amount":0.00313457,"currency":"BTC"},{"amount":1.5,"currency":"NBT"}]},{"time_stamp":1425946213633,"balance-not-on-order":[{"amount":0.00313457,"currency":"BTC"},{"amount":1.5,"currency":"NBT"}]},{"time_stamp":1425946343578,"balance-not-on-order":[{"amount":0.00314411,"currency":"BTC"},{"amount":1.5,"currency":"NBT"}]},{"time_stamp":1425946473642,"balance-not-on-order":[{"amount":0.00314411,"currency":"BTC"},{"amount":1.5,"currency":"NBT"}]},{"time_stamp":1425946603592,"balance-not-on-order":[{"amount":0.00314411,"currency":"BTC"},{"amount":1.5,"currency":"NBT"}]},{"time_stamp":1425946733723,"balance-not-on-order":[{"amount":0.00313359,"currency":"BTC"},{"amount":1.5,"currency":"NBT"}]},{"time_stamp":1425946993702,"balance-not-on-order":[{"amount":0.00313469,"currency":"BTC"},{"amount":1.5,"currency":"NBT"}]},{"time_stamp":1425947123770,"balance-not-on-order":[{"amount":0.00313491,"currency":"BTC"},{"amount":1.5,"currency":"NBT"}]},{"time_stamp":1425947253637,"balance-not-on-order":[{"amount":0.00313491,"currency":"BTC"},{"amount":1.5,"currency":"NBT"}]},{"time_stamp":1425947383590,"balance-not-on-order":[{"amount":0.00313491,"currency":"BTC"},{"amount":1.5,"currency":"NBT"}]},{"time_stamp":1425947513631,"balance-not-on-order":[{"amount":0.00315302,"currency":"BTC"},{"amount":1.5,"currency":"NBT"}]},{"time_stamp":1425947643731,"balance-not-on-order":[{"amount":0.00315302,"currency":"BTC"},{"amount":1.5,"currency":"NBT"}]},{"time_stamp":1425947903758,"balance-not-on-order":[{"amount":0.00314729,"currency":"BTC"},{"amount":1.5,"currency":"NBT"}]},{"time_stamp":1425948033612,"balance-not-on-order":[{"amount":0.00314038,"currency":"BTC"},{"amount":1.5,"currency":"NBT"}]},{"time_stamp":1425948163592,"balance-not-on-order":[{"amount":0.00313043,"currency":"BTC"},{"amount":1.5,"currency":"NBT"}]},{"time_stamp":1425948293604,"balance-not-on-order":[{"amount":0.00313043,"currency":"BTC"},{"amount":1.5,"currency":"NBT"}]},{"time_stamp":1425948423800,"balance-not-on-order":[{"amount":0.00312532,"currency":"BTC"},{"amount":1.5,"currency":"NBT"}]},{"time_stamp":1425948553709,"balance-not-on-order":[{"amount":0.00313829,"currency":"BTC"},{"amount":1.5,"currency":"NBT"}]},{"time_stamp":1425948683677,"balance-not-on-order":[{"amount":0.00312521,"currency":"BTC"},{"amount":1.5,"currency":"NBT"}]},{"time_stamp":1425948813636,"balance-not-on-order":[{"amount":0.00312521,"currency":"BTC"},{"amount":1.5,"currency":"NBT"}]},{"time_stamp":1425948943591,"balance-not-on-order":[{"amount":0.00312532,"currency":"BTC"},{"amount":1.5,"currency":"NBT"}]},{"time_stamp":1425949073661,"balance-not-on-order":[{"amount":0.00312532,"currency":"BTC"},{"amount":1.5,"currency":"NBT"}]},{"time_stamp":1425949333662,"balance-not-on-order":[{"amount":0.00312532,"currency":"BTC"},{"amount":1.5,"currency":"NBT"}]},{"time_stamp":1425949463858,"balance-not-on-order":[{"amount":0.00312532,"currency":"BTC"},{"amount":1.5,"currency":"NBT"}]},{"time_stamp":1425949593585,"balance-not-on-order":[{"amount":0.00313065,"currency":"BTC"},{"amount":1.5,"currency":"NBT"}]},{"time_stamp":1425949723654,"balance-not-on-order":[{"amount":0.00313065,"currency":"BTC"},{"amount":1.5,"currency":"NBT"}]},{"time_stamp":1425949853630,"balance-not-on-order":[{"amount":0.00313578,"currency":"BTC"},{"amount":1.5,"currency":"NBT"}]},{"time_stamp":1425949983750,"balance-not-on-order":[{"amount":0.00313578,"currency":"BTC"},{"amount":1.5,"currency":"NBT"}]},{"time_stamp":1425950244405,"balance-not-on-order":[{"amount":0.00313272,"currency":"BTC"},{"amount":1.5,"currency":"NBT"}]},{"time_stamp":1425950373664,"balance-not-on-order":[{"amount":0.00313272,"currency":"BTC"},{"amount":1.5,"currency":"NBT"}]},{"time_stamp":1425950503612,"balance-not-on-order":[{"amount":0.00312652,"currency":"BTC"},{"amount":1.5,"currency":"NBT"}]},{"time_stamp":1425950633621,"balance-not-on-order":[{"amount":0.00312652,"currency":"BTC"},{"amount":1.5,"currency":"NBT"}]},{"time_stamp":1425950763658,"balance-not-on-order":[{"amount":0.00312652,"currency":"BTC"},{"amount":1.5,"currency":"NBT"}]},{"time_stamp":1425950893832,"balance-not-on-order":[{"amount":0.00312652,"currency":"BTC"},{"amount":1.5,"currency":"NBT"}]},{"time_stamp":1425951023665,"balance-not-on-order":[{"amount":0.00312652,"currency":"BTC"},{"amount":1.5,"currency":"NBT"}]},{"time_stamp":1425951153882,"balance-not-on-order":[{"amount":0.00312652,"currency":"BTC"},{"amount":1.5,"currency":"NBT"}]},{"time_stamp":1425951283712,"balance-not-on-order":[{"amount":0.00312652,"currency":"BTC"},{"amount":1.5,"currency":"NBT"}]},{"time_stamp":1425951413606,"balance-not-on-order":[{"amount":0.00312555,"currency":"BTC"},{"amount":1.5,"currency":"NBT"}]},{"time_stamp":1425951673639,"balance-not-on-order":[{"amount":0.00312555,"currency":"BTC"},{"amount":1.5,"currency":"NBT"}]},{"time_stamp":1425951803617,"balance-not-on-order":[{"amount":0.00312566,"currency":"BTC"},{"amount":1.5,"currency":"NBT"}]},{"time_stamp":1425951933605,"balance-not-on-order":[{"amount":0.00312566,"currency":"BTC"},{"amount":1.5,"currency":"NBT"}]},{"time_stamp":1425952063628,"balance-not-on-order":[{"amount":0.00312566,"currency":"BTC"},{"amount":1.5,"currency":"NBT"}]},{"time_stamp":1425952194211,"balance-not-on-order":[{"amount":0.00312555,"currency":"BTC"},{"amount":1.5,"currency":"NBT"}]},{"time_stamp":1425952323592,"balance-not-on-order":[{"amount":0.00312555,"currency":"BTC"},{"amount":1.5,"currency":"NBT"}]},{"time_stamp":1425952583630,"balance-not-on-order":[{"amount":0.00312859,"currency":"BTC"},{"amount":1.5,"currency":"NBT"}]},{"time_stamp":1425952713683,"balance-not-on-order":[{"amount":0.00312859,"currency":"BTC"},{"amount":1.5,"currency":"NBT"}]},{"time_stamp":1425952843641,"balance-not-on-order":[{"amount":0.00312859,"currency":"BTC"},{"amount":1.5,"currency":"NBT"}]},{"time_stamp":1425952973983,"balance-not-on-order":[{"amount":0.00312859,"currency":"BTC"},{"amount":1.5,"currency":"NBT"}]},{"time_stamp":1425953103665,"balance-not-on-order":[{"amount":0.00312859,"currency":"BTC"},{"amount":1.5,"currency":"NBT"}]},{"time_stamp":1425953233611,"balance-not-on-order":[{"amount":0.0031262,"currency":"BTC"},{"amount":1.5,"currency":"NBT"}]},{"time_stamp":1425953363587,"balance-not-on-order":[{"amount":0.0031262,"currency":"BTC"},{"amount":1.5,"currency":"NBT"}]},{"time_stamp":1425953493668,"balance-not-on-order":[{"amount":0.0031262,"currency":"BTC"},{"amount":1.5,"currency":"NBT"}]},{"time_stamp":1425953623585,"balance-not-on-order":[{"amount":0.003125,"currency":"BTC"},{"amount":1.5,"currency":"NBT"}]},{"time_stamp":1425953754153,"balance-not-on-order":[{"amount":0.003125,"currency":"BTC"},{"amount":1.5,"currency":"NBT"}]},{"time_stamp":1425954013584,"balance-not-on-order":[{"amount":0.003125,"currency":"BTC"},{"amount":1.5,"currency":"NBT"}]},{"time_stamp":1425954143588,"balance-not-on-order":[{"amount":0.00312521,"currency":"BTC"},{"amount":1.5,"currency":"NBT"}]},{"time_stamp":1425954273613,"balance-not-on-order":[{"amount":0.00312511,"currency":"BTC"},{"amount":1.5,"currency":"NBT"}]},{"time_stamp":1425954403547,"balance-not-on-order":[{"amount":0.00312511,"currency":"BTC"},{"amount":1.5,"currency":"NBT"}]},{"time_stamp":1425954533561,"balance-not-on-order":[{"amount":0.00312511,"currency":"BTC"},{"amount":1.5,"currency":"NBT"}]},{"time_stamp":1425954664055,"balance-not-on-order":[{"amount":0.00312511,"currency":"BTC"},{"amount":1.5,"currency":"NBT"}]},{"time_stamp":1425954923662,"balance-not-on-order":[{"amount":0.00311419,"currency":"BTC"},{"amount":1.5,"currency":"NBT"}]},{"time_stamp":1425955053717,"balance-not-on-order":[{"amount":0.00311419,"currency":"BTC"},{"amount":1.5,"currency":"NBT"}]},{"time_stamp":1425955183586,"balance-not-on-order":[{"amount":0.00311193,"currency":"BTC"},{"amount":1.5,"currency":"NBT"}]},{"time_stamp":1425955313605,"balance-not-on-order":[{"amount":0.00311193,"currency":"BTC"},{"amount":1.5,"currency":"NBT"}]},{"time_stamp":1425955443774,"balance-not-on-order":[{"amount":0.00310442,"currency":"BTC"},{"amount":1.5,"currency":"NBT"}]},{"time_stamp":1425955573631,"balance-not-on-order":[{"amount":0.00310355,"currency":"BTC"},{"amount":1.5,"currency":"NBT"}]},{"time_stamp":1425955703665,"balance-not-on-order":[{"amount":0.00310355,"currency":"BTC"},{"amount":1.5,"currency":"NBT"}]},{"time_stamp":1425955833753,"balance-not-on-order":[{"amount":0.00310355,"currency":"BTC"},{"amount":1.5,"currency":"NBT"}]},{"time_stamp":1425955963609,"balance-not-on-order":[{"amount":0.00309098,"currency":"BTC"},{"amount":1.5,"currency":"NBT"}]},{"time_stamp":1425956093608,"balance-not-on-order":[{"amount":0.00309098,"currency":"BTC"},{"amount":1.5,"currency":"NBT"}]},{"time_stamp":1425956353732,"balance-not-on-order":[{"amount":0.00308949,"currency":"BTC"},{"amount":1.5,"currency":"NBT"}]},{"time_stamp":1425956483873,"balance-not-on-order":[{"amount":0.00308219,"currency":"BTC"},{"amount":1.5,"currency":"NBT"}]},{"time_stamp":1425956613618,"balance-not-on-order":[{"amount":0.00308219,"currency":"BTC"},{"amount":1.5,"currency":"NBT"}]},{"time_stamp":1425956743826,"balance-not-on-order":[{"amount":0.00308219,"currency":"BTC"},{"amount":1.5,"currency":"NBT"}]},{"time_stamp":1425956873647,"balance-not-on-order":[{"amount":0.00307021,"currency":"BTC"},{"amount":1.5,"currency":"NBT"}]},{"time_stamp":1425957003734,"balance-not-on-order":[{"amount":0.00307021,"currency":"BTC"},{"amount":1.5,"currency":"NBT"}]},{"time_stamp":1425957263665,"balance-not-on-order":[{"amount":0.00306853,"currency":"BTC"},{"amount":1.5,"currency":"NBT"}]},{"time_stamp":1425957393612,"balance-not-on-order":[{"amount":0.00306435,"currency":"BTC"},{"amount":1.5,"currency":"NBT"}]},{"time_stamp":1425957523590,"balance-not-on-order":[{"amount":0.00306122,"currency":"BTC"},{"amount":1.5,"currency":"NBT"}]},{"time_stamp":1425957653770,"balance-not-on-order":[{"amount":0.00306122,"currency":"BTC"},{"amount":1.5,"currency":"NBT"}]},{"time_stamp":1425957783815,"balance-not-on-order":[{"amount":0.00306122,"currency":"BTC"},{"amount":1.5,"currency":"NBT"}]},{"time_stamp":1425957913697,"balance-not-on-order":[{"amount":0.00306383,"currency":"BTC"},{"amount":1.5,"currency":"NBT"}]},{"time_stamp":1425958043666,"balance-not-on-order":[{"amount":0.00308198,"currency":"BTC"},{"amount":1.5,"currency":"NBT"}]},{"time_stamp":1425958173613,"balance-not-on-order":[{"amount":0.00308198,"currency":"BTC"},{"amount":1.5,"currency":"NBT"}]},{"time_stamp":1425958303649,"balance-not-on-order":[{"amount":0.00308198,"currency":"BTC"},{"amount":1.5,"currency":"NBT"}]},{"time_stamp":1425958433652,"balance-not-on-order":[{"amount":0.00308219,"currency":"BTC"},{"amount":1.5,"currency":"NBT"}]},{"time_stamp":1425958693640,"balance-not-on-order":[{"amount":0.00308219,"currency":"BTC"},{"amount":1.5,"currency":"NBT"}]},{"time_stamp":1425958823623,"balance-not-on-order":[{"amount":0.00308219,"currency":"BTC"},{"amount":1.5,"currency":"NBT"}]},{"time_stamp":1425958953610,"balance-not-on-order":[{"amount":0.00308188,"currency":"BTC"},{"amount":1.5,"currency":"NBT"}]},{"time_stamp":1425959083744,"balance-not-on-order":[{"amount":0.00308188,"currency":"BTC"},{"amount":1.5,"currency":"NBT"}]},{"time_stamp":1425959213695,"balance-not-on-order":[{"amount":0.00308188,"currency":"BTC"},{"amount":1.5,"currency":"NBT"}]},{"time_stamp":1425959344047,"balance-not-on-order":[{"amount":0.00308779,"currency":"BTC"},{"amount":1.5,"currency":"NBT"}]},{"time_stamp":1425959604222,"balance-not-on-order":[{"amount":0.00308801,"currency":"BTC"},{"amount":1.5,"currency":"NBT"}]},{"time_stamp":1425959733613,"balance-not-on-order":[{"amount":0.00308409,"currency":"BTC"},{"amount":1.5,"currency":"NBT"}]},{"time_stamp":1425959863601,"balance-not-on-order":[{"amount":0.00309502,"currency":"BTC"},{"amount":1.5,"currency":"NBT"}]},{"time_stamp":1425959993638,"balance-not-on-order":[{"amount":0.00309502,"currency":"BTC"},{"amount":1.5,"currency":"NBT"}]},{"time_stamp":1425960123942,"balance-not-on-order":[{"amount":0.00309502,"currency":"BTC"},{"amount":1.5,"currency":"NBT"}]},{"time_stamp":1425960253619,"balance-not-on-order":[{"amount":0.00310366,"currency":"BTC"},{"amount":1.5,"currency":"NBT"}]},{"time_stamp":1425960383683,"balance-not-on-order":[{"amount":0.00310366,"currency":"BTC"},{"amount":1.5,"currency":"NBT"}]},{"time_stamp":1425960513622,"balance-not-on-order":[{"amount":0.00310366,"currency":"BTC"},{"amount":1.5,"currency":"NBT"}]},{"time_stamp":1425960643598,"balance-not-on-order":[{"amount":0.00310366,"currency":"BTC"},{"amount":1.5,"currency":"NBT"}]},{"time_stamp":1425960773702,"balance-not-on-order":[{"amount":0.00310398,"currency":"BTC"},{"amount":1.5,"currency":"NBT"}]},{"time_stamp":1425961033968,"balance-not-on-order":[{"amount":0.00309353,"currency":"BTC"},{"amount":1.5,"currency":"NBT"}]},{"time_stamp":1425961163755,"balance-not-on-order":[{"amount":0.00309992,"currency":"BTC"},{"amount":1.5,"currency":"NBT"}]},{"time_stamp":1425961293567,"balance-not-on-order":[{"amount":0.00309427,"currency":"BTC"},{"amount":1.5,"currency":"NBT"}]},{"time_stamp":1425961423706,"balance-not-on-order":[{"amount":0.00309427,"currency":"BTC"},{"amount":1.5,"currency":"NBT"}]},{"time_stamp":1425961553614,"balance-not-on-order":[{"amount":0.00309619,"currency":"BTC"},{"amount":1.5,"currency":"NBT"}]},{"time_stamp":1425961683802,"balance-not-on-order":[{"amount":0.00308812,"currency":"BTC"},{"amount":1.5,"currency":"NBT"}]},{"time_stamp":1425961943780,"balance-not-on-order":[{"amount":0.00309279,"currency":"BTC"},{"amount":1.5,"currency":"NBT"}]},{"time_stamp":1425962073694,"balance-not-on-order":[{"amount":0.00309279,"currency":"BTC"},{"amount":1.5,"currency":"NBT"}]},{"time_stamp":1425962203868,"balance-not-on-order":[{"amount":0.00309704,"currency":"BTC"},{"amount":1.5,"currency":"NBT"}]},{"time_stamp":1425962333677,"balance-not-on-order":[{"amount":0.00309704,"currency":"BTC"},{"amount":1.5,"currency":"NBT"}]},{"time_stamp":1425962463626,"balance-not-on-order":[{"amount":0.00309672,"currency":"BTC"},{"amount":1.5,"currency":"NBT"}]},{"time_stamp":1425962593629,"balance-not-on-order":[{"amount":0.00309672,"currency":"BTC"},{"amount":1.5,"currency":"NBT"}]},{"time_stamp":1425962723842,"balance-not-on-order":[{"amount":0.00311096,"currency":"BTC"},{"amount":1.5,"currency":"NBT"}]},{"time_stamp":1425962853665,"balance-not-on-order":[{"amount":0.00311096,"currency":"BTC"},{"amount":1.5,"currency":"NBT"}]},{"time_stamp":1425962983779,"balance-not-on-order":[{"amount":0.00310935,"currency":"BTC"},{"amount":1.5,"currency":"NBT"}]},{"time_stamp":1425963113808,"balance-not-on-order":[{"amount":0.0031027,"currency":"BTC"},{"amount":1.5,"currency":"NBT"}]},{"time_stamp":1425963373691,"balance-not-on-order":[{"amount":0.00308229,"currency":"BTC"},{"amount":1.5,"currency":"NBT"}]},{"time_stamp":1425963503629,"balance-not-on-order":[{"amount":0.00308282,"currency":"BTC"},{"amount":1.5,"currency":"NBT"}]},{"time_stamp":1425963633583,"balance-not-on-order":[{"amount":0.00308282,"currency":"BTC"},{"amount":1.5,"currency":"NBT"}]},{"time_stamp":1425963763744,"balance-not-on-order":[{"amount":0.00308282,"currency":"BTC"},{"amount":1.5,"currency":"NBT"}]},{"time_stamp":1425963893704,"balance-not-on-order":[{"amount":0.00308082,"currency":"BTC"},{"amount":1.5,"currency":"NBT"}]},{"time_stamp":1425964023611,"balance-not-on-order":[{"amount":0.00307283,"currency":"BTC"},{"amount":1.5,"currency":"NBT"}]},{"time_stamp":1425964283720,"balance-not-on-order":[{"amount":0.00308103,"currency":"BTC"},{"amount":1.5,"currency":"NBT"}]},{"time_stamp":1425964413681,"balance-not-on-order":[{"amount":0.00308103,"currency":"BTC"},{"amount":1.5,"currency":"NBT"}]},{"time_stamp":1425964543743,"balance-not-on-order":[{"amount":0.00308282,"currency":"BTC"},{"amount":1.5,"currency":"NBT"}]},{"time_stamp":1425964673739,"balance-not-on-order":[{"amount":0.00308282,"currency":"BTC"},{"amount":1.5,"currency":"NBT"}]},{"time_stamp":1425964803614,"balance-not-on-order":[{"amount":0.00308282,"currency":"BTC"},{"amount":1.5,"currency":"NBT"}]},{"time_stamp":1425964933596,"balance-not-on-order":[{"amount":0.00308039,"currency":"BTC"},{"amount":1.5,"currency":"NBT"}]},{"time_stamp":1425965063659,"balance-not-on-order":[{"amount":0.00307398,"currency":"BTC"},{"amount":1.5,"currency":"NBT"}]},{"time_stamp":1425965193549,"balance-not-on-order":[{"amount":0.00307398,"currency":"BTC"},{"amount":1.5,"currency":"NBT"}]},{"time_stamp":1425965323611,"balance-not-on-order":[{"amount":0.00308409,"currency":"BTC"},{"amount":1.5,"currency":"NBT"}]},{"time_stamp":1425965453566,"balance-not-on-order":[{"amount":0.00307703,"currency":"BTC"},{"amount":1.5,"currency":"NBT"}]},{"time_stamp":1425965713697,"balance-not-on-order":[{"amount":0.00308367,"currency":"BTC"},{"amount":1.5,"currency":"NBT"}]},{"time_stamp":1425965843818,"balance-not-on-order":[{"amount":0.00308367,"currency":"BTC"},{"amount":1.5,"currency":"NBT"}]},{"time_stamp":1425965973939,"balance-not-on-order":[{"amount":0.00307409,"currency":"BTC"},{"amount":1.5,"currency":"NBT"}]},{"time_stamp":1425966103964,"balance-not-on-order":[{"amount":0.00307409,"currency":"BTC"},{"amount":1.5,"currency":"NBT"}]},{"time_stamp":1425966233915,"balance-not-on-order":[{"amount":0.00307409,"currency":"BTC"},{"amount":1.5,"currency":"NBT"}]},{"time_stamp":1425966364165,"balance-not-on-order":[{"amount":0.00307451,"currency":"BTC"},{"amount":1.5,"currency":"NBT"}]},{"time_stamp":1425966623613,"balance-not-on-order":[{"amount":0.00308219,"currency":"BTC"},{"amount":1.5,"currency":"NBT"}]},{"time_stamp":1425966753724,"balance-not-on-order":[{"amount":0.00308219,"currency":"BTC"},{"amount":1.5,"currency":"NBT"}]},{"time_stamp":1425966883856,"balance-not-on-order":[{"amount":0.00307703,"currency":"BTC"},{"amount":1.5,"currency":"NBT"}]},{"time_stamp":1425967013669,"balance-not-on-order":[{"amount":0.00307703,"currency":"BTC"},{"amount":1.5,"currency":"NBT"}]},{"time_stamp":1425967143649,"balance-not-on-order":[{"amount":0.00308525,"currency":"BTC"},{"amount":1.5,"currency":"NBT"}]},{"time_stamp":1425967274317,"balance-not-on-order":[{"amount":0.00307692,"currency":"BTC"},{"amount":1.5,"currency":"NBT"}]},{"time_stamp":1425967534068,"balance-not-on-order":[{"amount":0.00307692,"currency":"BTC"},{"amount":1.5,"currency":"NBT"}]},{"time_stamp":1425967663620,"balance-not-on-order":[{"amount":0.00307692,"currency":"BTC"},{"amount":1.5,"currency":"NBT"}]},{"time_stamp":1425967793617,"balance-not-on-order":[{"amount":0.00307461,"currency":"BTC"},{"amount":1.5,"currency":"NBT"}]},{"time_stamp":1425968053845,"balance-not-on-order":[{"amount":0.00308114,"currency":"BTC"},{"amount":1.5,"currency":"NBT"}]},{"time_stamp":1425968183903,"balance-not-on-order":[{"amount":0.00307472,"currency":"BTC"},{"amount":1.5,"currency":"NBT"}]},{"time_stamp":1425968313738,"balance-not-on-order":[{"amount":0.00307482,"currency":"BTC"},{"amount":1.5,"currency":"NBT"}]},{"time_stamp":1425968443631,"balance-not-on-order":[{"amount":0.00307482,"currency":"BTC"},{"amount":1.5,"currency":"NBT"}]},{"time_stamp":1425968573698,"balance-not-on-order":[{"amount":0.00307482,"currency":"BTC"},{"amount":1.5,"currency":"NBT"}]},{"time_stamp":1425968703622,"balance-not-on-order":[{"amount":0.00308124,"currency":"BTC"},{"amount":1.5,"currency":"NBT"}]},{"time_stamp":1425968963645,"balance-not-on-order":[{"amount":0.0030842,"currency":"BTC"},{"amount":1.5,"currency":"NBT"}]},{"time_stamp":1425969093784,"balance-not-on-order":[{"amount":0.00308367,"currency":"BTC"},{"amount":1.5,"currency":"NBT"}]}]}
